{
  "version": 1,
  "generatedAt": "2026-07-02T09:23:57.521Z",
  "offers": {
    "ecoflow-delta-pro": {
      "bol": {
        "available": null,
        "status": "manual",
        "checkedAt": "2026-07-02T09:23:19.219Z",
        "note": "Bol blokkeert bots (403) — handmatig in bol-urls.ts"
      }
    },
    "ecoflow-delta-pro-3": {
      "bol": {
        "available": null,
        "status": "manual",
        "checkedAt": "2026-07-02T09:23:19.219Z",
        "note": "Handmatig bijgewerkt in bol-urls.ts"
      },
      "ecoflow": {
        "price": 3299,
        "available": true,
        "status": "ok",
        "checkedAt": "2026-07-02T09:23:19.219Z",
        "source": "shopify",
        "title": "DELTA Pro 3",
        "image": "https://cdn.shopify.com/s/files/1/0963/3965/6980/files/ecoflow-delta-pro-3-portable-power-station-58715243872599.png"
      }
    },
    "anker-solix-f3800": {
      "bol": {
        "available": null,
        "status": "manual",
        "checkedAt": "2026-07-02T09:23:19.552Z",
        "note": "Handmatig bijgewerkt in bol-urls.ts"
      }
    },
    "bluetti-elite-300": {
      "bol": {
        "available": null,
        "status": "manual",
        "checkedAt": "2026-07-02T09:23:19.552Z",
        "note": "Handmatig bijgewerkt in bol-urls.ts"
      },
      "bluetti": {
        "price": 1649,
        "available": true,
        "status": "ok",
        "checkedAt": "2026-07-02T09:23:19.552Z",
        "source": "shopify",
        "title": "Elite 300 | 2.400W 3.014,4Wh Power Station",
        "image": "https://cdn.shopify.com/s/files/1/0566/6396/5893/files/bluetti-elite-300-power-station.webp"
      }
    },
    "jackery-explorer-2000-plus": {
      "bol": {
        "available": null,
        "status": "manual",
        "checkedAt": "2026-07-02T09:23:19.985Z",
        "note": "Handmatig bijgewerkt in bol-urls.ts"
      }
    },
    "ecoflow-delta-2-max": {
      "bol": {
        "available": null,
        "status": "manual",
        "checkedAt": "2026-07-02T09:23:19.985Z",
        "note": "Handmatig bijgewerkt in bol-urls.ts"
      },
      "amazon": {
        "available": null,
        "status": "ok",
        "checkedAt": "2026-07-02T09:23:19.985Z",
        "source": "amazon"
      },
      "ecoflow": {
        "price": 949,
        "available": true,
        "status": "ok",
        "checkedAt": "2026-07-02T09:23:22.733Z",
        "source": "shopify",
        "title": "DELTA 2 Max",
        "image": "https://cdn.shopify.com/s/files/1/0963/3965/6980/files/ecoflow-delta-2-max-portable-power-station-51305159590231.png"
      }
    },
    "ecoflow-delta-3-max": {
      "bol": {
        "available": null,
        "status": "manual",
        "checkedAt": "2026-07-02T09:23:22.873Z",
        "note": "Handmatig bijgewerkt in bol-urls.ts"
      },
      "ecoflow": {
        "price": 1299,
        "available": true,
        "status": "ok",
        "checkedAt": "2026-07-02T09:23:22.873Z",
        "source": "shopify",
        "title": "DELTA 3 Max (2048Wh) / Geen accessoire",
        "image": "https://cdn.shopify.com/s/files/1/0963/3965/6980/files/ecoflow-delta-3-max-series-portable-power-station-1197150547.png"
      }
    },
    "bluetti-elite-200-v2": {
      "bol": {
        "available": null,
        "status": "manual",
        "checkedAt": "2026-07-02T09:23:23.046Z",
        "note": "Handmatig bijgewerkt in bol-urls.ts"
      },
      "bluetti": {
        "price": 1299,
        "available": true,
        "status": "ok",
        "checkedAt": "2026-07-02T09:23:23.046Z",
        "source": "shopify",
        "title": "Elite 200 V2 | 2.600W 2.073,6Wh Power Station",
        "image": "https://cdn.shopify.com/s/files/1/0566/6396/5893/files/Elite-200-v2-IFA-2025.webp"
      }
    },
    "ecoflow-delta-2": {
      "bol": {
        "available": null,
        "status": "manual",
        "checkedAt": "2026-07-02T09:23:23.202Z",
        "note": "Handmatig bijgewerkt in bol-urls.ts"
      },
      "amazon": {
        "price": 569,
        "available": true,
        "status": "ok",
        "checkedAt": "2026-07-02T09:23:23.203Z",
        "source": "amazon",
        "title": "EcoFlow DELTA 2 draagbaar elektrisch station met schaalbare capaciteit van 1-3 kWh, LFP-batterij, slechts enkele kleine gebreken in de verpakking, het product is niet gebruikt (gereviseerd)",
        "image": "https://m.media-amazon.com/images/I/51flNVzTtWL._AC_SL1500_.jpg"
      },
      "ecoflow": {
        "price": 499,
        "available": true,
        "status": "ok",
        "checkedAt": "2026-07-02T09:23:26.658Z",
        "source": "shopify",
        "title": "DELTA 2",
        "image": "https://cdn.shopify.com/s/files/1/0963/3965/6980/files/ecoflow-delta-2-portable-power-station-52097645347159.png"
      }
    },
    "ecoflow-delta-3-plus": {
      "bol": {
        "available": null,
        "status": "manual",
        "checkedAt": "2026-07-02T09:23:26.838Z",
        "note": "Handmatig bijgewerkt in bol-urls.ts"
      },
      "amazon": {
        "available": null,
        "status": "ok",
        "checkedAt": "2026-07-02T09:23:26.838Z",
        "source": "amazon"
      },
      "ecoflow": {
        "price": 849,
        "available": true,
        "status": "ok",
        "checkedAt": "2026-07-02T09:23:29.482Z",
        "source": "shopify",
        "title": "DELTA 3 Plus / Geen accessoire",
        "image": "https://cdn.shopify.com/s/files/1/0963/3965/6980/files/ecoflow-delta-3-series-portable-power-station-60905350299991.png"
      }
    },
    "ecoflow-delta-3-classic": {
      "amazon": {
        "available": null,
        "status": "ok",
        "checkedAt": "2026-07-02T09:23:29.681Z",
        "source": "amazon"
      },
      "ecoflow": {
        "price": 519,
        "available": true,
        "status": "ok",
        "checkedAt": "2026-07-02T09:23:32.318Z",
        "source": "shopify",
        "title": "DELTA 3 Classic",
        "image": "https://cdn.shopify.com/s/files/1/0963/3965/6980/files/DELTA3Classic.png"
      }
    },
    "ecoflow-delta-3": {
      "amazon": {
        "available": null,
        "status": "ok",
        "checkedAt": "2026-07-02T09:23:32.471Z",
        "source": "amazon"
      },
      "ecoflow": {
        "price": 749,
        "available": true,
        "status": "ok",
        "checkedAt": "2026-07-02T09:23:35.152Z",
        "source": "shopify",
        "title": "DELTA 3 / Geen accessoire",
        "image": "https://cdn.shopify.com/s/files/1/0963/3965/6980/files/ecoflow-delta-3-series-portable-power-station-60905350299991.png"
      }
    },
    "anker-solix-c1000": {
      "bol": {
        "available": null,
        "status": "manual",
        "checkedAt": "2026-07-02T09:23:35.263Z",
        "note": "Handmatig bijgewerkt in bol-urls.ts"
      },
      "amazon": {
        "available": null,
        "status": "ok",
        "checkedAt": "2026-07-02T09:23:35.263Z",
        "source": "amazon"
      }
    },
    "jackery-explorer-1000-v2": {
      "bol": {
        "available": null,
        "status": "manual",
        "checkedAt": "2026-07-02T09:23:37.946Z",
        "note": "Handmatig bijgewerkt in bol-urls.ts"
      },
      "amazon": {
        "available": null,
        "status": "ok",
        "checkedAt": "2026-07-02T09:23:37.946Z",
        "source": "amazon"
      }
    },
    "anker-solix-c800x": {
      "bol": {
        "available": null,
        "status": "manual",
        "checkedAt": "2026-07-02T09:23:40.628Z",
        "note": "Handmatig bijgewerkt in bol-urls.ts"
      }
    },
    "ecoflow-river-2-pro": {
      "amazon": {
        "available": null,
        "status": "ok",
        "checkedAt": "2026-07-02T09:23:40.628Z",
        "source": "amazon"
      },
      "ecoflow": {
        "price": 399,
        "available": true,
        "status": "ok",
        "checkedAt": "2026-07-02T09:23:43.263Z",
        "source": "shopify",
        "title": "RIVER 2 Pro (ledenprijs)",
        "image": "https://cdn.shopify.com/s/files/1/0963/3965/6980/files/products_ecoflow-river-2-pro-portable-power-station-42466006433956.png"
      }
    },
    "ecoflow-river-3-plus": {
      "amazon": {
        "available": null,
        "status": "ok",
        "checkedAt": "2026-07-02T09:23:43.687Z",
        "source": "amazon"
      },
      "ecoflow": {
        "price": 299,
        "available": true,
        "status": "ok",
        "checkedAt": "2026-07-02T09:23:46.369Z",
        "source": "shopify",
        "title": "RIVIER 3 Plus / /",
        "image": "https://cdn.shopify.com/s/files/1/0963/3965/6980/files/ecoflow-river-3-plus-portable-power-station-1146556335.png"
      }
    },
    "anker-solix-c300": {
      "bol": {
        "available": null,
        "status": "manual",
        "checkedAt": "2026-07-02T09:23:46.504Z",
        "note": "Handmatig bijgewerkt in bol-urls.ts"
      },
      "amazon": {
        "available": null,
        "status": "ok",
        "checkedAt": "2026-07-02T09:23:46.504Z",
        "source": "amazon"
      }
    },
    "ecoflow-river-2-max": {
      "amazon": {
        "available": null,
        "status": "ok",
        "checkedAt": "2026-07-02T09:23:49.191Z",
        "source": "amazon"
      },
      "ecoflow": {
        "price": 299,
        "available": true,
        "status": "ok",
        "checkedAt": "2026-07-02T09:23:51.827Z",
        "source": "shopify",
        "title": "RIVIER 2 Max",
        "image": "https://cdn.shopify.com/s/files/1/0963/3965/6980/files/products_ecoflow-river-2-max-portable-power-station-42462847041700.png"
      }
    },
    "jackery-explorer-500-v2": {
      "bol": {
        "available": null,
        "status": "manual",
        "checkedAt": "2026-07-02T09:23:52.086Z",
        "note": "Handmatig bijgewerkt in bol-urls.ts"
      },
      "amazon": {
        "available": null,
        "status": "ok",
        "checkedAt": "2026-07-02T09:23:52.086Z",
        "source": "amazon"
      }
    },
    "anker-solix-f1500": {
      "bol": {
        "available": null,
        "status": "manual",
        "checkedAt": "2026-07-02T09:23:54.885Z",
        "note": "Handmatig bijgewerkt in bol-urls.ts"
      },
      "amazon": {
        "available": null,
        "status": "ok",
        "checkedAt": "2026-07-02T09:23:54.885Z",
        "source": "amazon"
      }
    }
  }
}
